dummy_lambda/func/__init__.py
dummy_lambda/func/main.py
lpipe/__init__.py
lpipe/_version.py
lpipe/action.py
lpipe/exceptions.py
lpipe/logging.py
lpipe/normalize.py
lpipe/payload.py
lpipe/pipeline.py
lpipe/queue.py
lpipe/signature.py
lpipe/testing.py
lpipe/utils.py
lpipe/contrib/__init__.py
lpipe/contrib/boto3.py
lpipe/contrib/kinesis.py
lpipe/contrib/mindictive.py
lpipe/contrib/sentry.py
lpipe/contrib/sqs.py
lpipe-4.2.0.dist-info/LICENSE
lpipe-4.2.0.dist-info/METADATA
lpipe-4.2.0.dist-info/WHEEL
lpipe-4.2.0.dist-info/top_level.txt
lpipe-4.2.0.dist-info/RECORD
