Metadata-Version: 2.1
Name: lpipe
Version: 4.2.0
Summary: AWS Lambda framework for writing clear, minimal Python FAAS
Home-page: https://github.com/mintel/lpipe
Author: Charlie Mathews
Author-email: cmathews@mintel.com
Maintainer: Charlie Mathews
Maintainer-email: cmathews@mintel.com
License: APACHE
Project-URL: Bug Tracker, https://github.com/mintel/lpipe/issues
Project-URL: Source Code, https://github.com/mintel/lpipe
Platform: UNKNOWN
Classifier: Development Status :: 5 - Production/Stable
Classifier: Intended Audience :: Developers
Classifier: Topic :: Software Development :: Libraries :: Application Frameworks
Classifier: Programming Language :: Python :: 3
Classifier: Programming Language :: Python :: 3.6
Classifier: Programming Language :: Python :: 3.7
Classifier: Programming Language :: Python :: 3.8
Classifier: Operating System :: OS Independent
Classifier: License :: OSI Approved :: Apache Software License
Requires-Python: >=3.6
Requires-Dist: backoff
Requires-Dist: boto3
Requires-Dist: python-dateutil
Requires-Dist: requests
Requires-Dist: structlog
Provides-Extra: sentry
Requires-Dist: sentry-sdk ; extra == 'sentry'
Requires-Dist: python-decouple ; extra == 'sentry'
